fountains/__init__.py
fountains/fountains.py
fountains-3.0.1.dist-info/licenses/LICENSE
fountains-3.0.1.dist-info/METADATA
fountains-3.0.1.dist-info/WHEEL
fountains-3.0.1.dist-info/top_level.txt
fountains-3.0.1.dist-info/RECORD
