Metadata-Version: 2.4
Name: fountains
Version: 3.0.1
Summary: Python library for generating and concisely specifying reproducible pseudorandom binary data for unit testing.
Author: Andrei Lapets
Author-email: a@lapets.io
License-Expression: MIT
Project-URL: Repository, https://github.com/reity/fountains
Project-URL: Documentation, https://fountains.readthedocs.io
Requires-Python: >=3.9
License-File: LICENSE
Requires-Dist: bitlist~=2.0
Provides-Extra: docs
Requires-Dist: toml~=0.10.2; extra == "docs"
Requires-Dist: sphinx~=7.4; extra == "docs"
Requires-Dist: sphinx-rtd-theme~=3.0; extra == "docs"
Requires-Dist: sphinx-autodoc-typehints~=2.3; extra == "docs"
Provides-Extra: test
Requires-Dist: pytest~=8.4; extra == "test"
Requires-Dist: pytest-cov~=7.0; extra == "test"
Provides-Extra: lint
Requires-Dist: pylint~=3.3; extra == "lint"
Provides-Extra: coveralls
Requires-Dist: coveralls~=4.0; extra == "coveralls"
Provides-Extra: publish
Requires-Dist: build~=1.3; extra == "publish"
Requires-Dist: twine~=4.0; extra == "publish"
Dynamic: license-file
